README.md
setup.py
qwiic_exporter/qwiic_exporter.py
qwiic_exporter/test_qwiic_exporter.py
qwiic_exporter.egg-info/PKG-INFO
qwiic_exporter.egg-info/SOURCES.txt
qwiic_exporter.egg-info/dependency_links.txt
qwiic_exporter.egg-info/entry_points.txt
qwiic_exporter.egg-info/requires.txt
qwiic_exporter.egg-info/top_level.txt