Metadata-Version: 2.1
Name: qwiic-exporter
Version: 0.2.0
Summary: QwiicExpoter is a Prometheus exporter for SparkFun QWIIC sensor shield Artemis OpenLog.
Home-page: https://github.com/tykling/QwiicExporter
Author: Thomas Steen Rasmussen
Author-email: thomas@gibfest.dk
License: BSD License
Platform: UNKNOWN
Classifier: Programming Language :: Python :: 3.7
Classifier: Programming Language :: Python :: 3.8
Classifier: License :: OSI Approved :: BSD License
Classifier: Operating System :: OS Independent
Requires-Python: >=3.7
